discosnow/__init__.py
discosnow/discosnow.py
discosnow-0.0.5.dist-info/LICENSE
discosnow-0.0.5.dist-info/METADATA
discosnow-0.0.5.dist-info/WHEEL
discosnow-0.0.5.dist-info/top_level.txt
discosnow-0.0.5.dist-info/RECORD
