Metadata-Version: 2.1
Name: discosnow
Version: 0.0.5
Summary: A simple tools comvert from discord id to datetime
Home-page: https://github.com/being24/discord-snowflake
Author: being24
Author-email: being24@gmail.com
License: UNKNOWN
Platform: UNKNOWN
Classifier: Programming Language :: Python :: 3.7
Classifier: License :: OSI Approved :: MIT License
Classifier: Operating System :: OS Independent
